ou_tm351_jl_extensions/__init__.py
ou_tm351_jl_extensions-0.2.9.dist-info/LICENSE
ou_tm351_jl_extensions-0.2.9.dist-info/METADATA
ou_tm351_jl_extensions-0.2.9.dist-info/WHEEL
ou_tm351_jl_extensions-0.2.9.dist-info/RECORD
