Metadata-Version: 2.1
Name: ou-tm351-jl-extensions
Version: 0.2.9
Summary: 
Author: Tony Hirst
Author-email: tony.hirst@gmail.com
Requires-Python: >=3.8,<3.13
Classifier: Programming Language :: Python :: 3
Classifier: Programming Language :: Python :: 3.8
Classifier: Programming Language :: Python :: 3.9
Classifier: Programming Language :: Python :: 3.10
Classifier: Programming Language :: Python :: 3.11
Classifier: Programming Language :: Python :: 3.12
Requires-Dist: black (>=24.4.2,<25.0.0)
Requires-Dist: isort (>=5.13.2,<6.0.0)
Requires-Dist: jupyter-archive (>=3.4.0,<4.0.0)
Requires-Dist: jupyter-compare-view (>=0.2.4,<0.3.0)
Requires-Dist: jupyterlab (>=4.1)
Requires-Dist: jupyterlab-cell-status-extension (>=0.2.2,<0.3.0)
Requires-Dist: jupyterlab-code-formatter (>=2.2.1,<3.0.0)
Requires-Dist: jupyterlab-empinken-extension (>=0.6.0,<0.7.0)
Requires-Dist: jupyterlab-filesystem-access (>=0.6.0,<0.7.0)
Requires-Dist: jupyterlab-geojson (>=3.3.1,<4.0.0)
Requires-Dist: jupyterlab-git (>=0.50.1,<0.51.0)
Requires-Dist: jupyterlab-language-pack-fr-fr (>=4.1.post2,<5.0)
Requires-Dist: jupyterlab-language-pack-zh-cn (>=4.1.post2,<5.0)
Requires-Dist: jupyterlab-myst (>=2.4.0,<3.0.0)
Requires-Dist: jupyterlab-ou-brand-extension (>=0.2.3,<0.3.0)
Requires-Dist: jupyterlab-skip-traceback (>=5.1.0,<6.0.0)
Requires-Dist: jupyterlab-spellchecker (>=0.8.4,<0.9.0)
Requires-Dist: jupyterlab-unfold (>=0.3.0,<0.4.0)
Requires-Dist: jupyterlab_execute_time (>=3.1.2,<4.0.0)
Requires-Dist: jupytext (>=1.16.0,<2.0.0)
